{
	"info": {
		"_postman_id": "423b8e39-6b7a-4a19-9e31-4217ba36bae0",
		"name": "Api Musicas",
		"schema": "https://schema.getpostman.com/json/collection/v2.1.0/collection.json"
	},
	"item": [
		{
			"name": "Users",
			"item": [
				{
					"name": "Show All Users",
					"request": {
						"method": "GET",
						"header": [
							{
								"key": "accept",
								"value": "application/json"
							}
						],
						"url": {
							"raw": "http://localhost:8080/User",
							"protocol": "http",
							"host": [
								"localhost"
							],
							"port": "8080",
							"path": [
								"User"
							]
						}
					},
					"response": []
				},
				{
					"name": "Send User",
					"request": {
						"method": "POST",
						"header": [
							{
								"key": "accept",
								"value": "application/json"
							},
							{
								"key": "Content-Type",
								"value": "application/json"
							}
						],
						"body": {
							"mode": "raw",
							"raw": "{\"id\":34,\"nome\":\"Pedro\",\"pais\":\"Portugal\",\"idade\":50,\"email\":\"pedro@gmail.com\"}"
						},
						"url": {
							"raw": "http://localhost:8080/User",
							"protocol": "http",
							"host": [
								"localhost"
							],
							"port": "8080",
							"path": [
								"User"
							]
						}
					},
					"response": []
				},
				{
					"name": "Get User ID",
					"request": {
						"method": "GET",
						"header": [
							{
								"key": "accept",
								"value": "application/json"
							}
						],
						"url": {
							"raw": "http://localhost:8080/Users/2",
							"protocol": "http",
							"host": [
								"localhost"
							],
							"port": "8080",
							"path": [
								"Users",
								"2"
							]
						}
					},
					"response": []
				},
				{
					"name": "Update User ID",
					"request": {
						"method": "PUT",
						"header": [
							{
								"key": "accept",
								"value": "application/json"
							},
							{
								"key": "Content-Type",
								"value": "application/json"
							}
						],
						"body": {
							"mode": "raw",
							"raw": "{\"id\":1,\"nome\":\"Pedro\",\"pais\":\"Portuggal\",\"idade\":30,\"email\":\"pedro@gmail.com\"}"
						},
						"url": {
							"raw": "http://localhost:8080/Users/1",
							"protocol": "http",
							"host": [
								"localhost"
							],
							"port": "8080",
							"path": [
								"Users",
								"1"
							]
						}
					},
					"response": []
				},
				{
					"name": "Delete User ID",
					"request": {
						"method": "DELETE",
						"header": [
							{
								"key": "accept",
								"value": "*/*"
							}
						],
						"url": {
							"raw": "http://localhost:8080/Users/2",
							"protocol": "http",
							"host": [
								"localhost"
							],
							"port": "8080",
							"path": [
								"Users",
								"2"
							]
						}
					},
					"response": []
				}
			]
		},
		{
			"name": "Artista",
			"item": [
				{
					"name": "Show All Artists",
					"request": {
						"method": "GET",
						"header": [
							{
								"key": "accept",
								"value": "application/json"
							}
						],
						"url": {
							"raw": "http://localhost:8080/Artista",
							"protocol": "http",
							"host": [
								"localhost"
							],
							"port": "8080",
							"path": [
								"Artista"
							]
						}
					},
					"response": []
				},
				{
					"name": "Create Artist",
					"request": {
						"method": "POST",
						"header": [
							{
								"key": "accept",
								"value": "application/json"
							},
							{
								"key": "Content-Type",
								"value": "application/json"
							}
						],
						"body": {
							"mode": "raw",
							"raw": "{\"id\":1,\"nomeartista\":\"Matue\",\"pais\":\"Brasil\"}"
						},
						"url": {
							"raw": "http://localhost:8080/Artista",
							"protocol": "http",
							"host": [
								"localhost"
							],
							"port": "8080",
							"path": [
								"Artista"
							]
						}
					},
					"response": []
				},
				{
					"name": "Show Artist ID",
					"request": {
						"method": "GET",
						"header": [
							{
								"key": "accept",
								"value": "application/json"
							}
						],
						"url": {
							"raw": "http://localhost:8080/Artistas/1",
							"protocol": "http",
							"host": [
								"localhost"
							],
							"port": "8080",
							"path": [
								"Artistas",
								"1"
							]
						}
					},
					"response": []
				},
				{
					"name": "Update Artist ID",
					"request": {
						"method": "PUT",
						"header": [
							{
								"key": "accept",
								"value": "application/json"
							},
							{
								"key": "Content-Type",
								"value": "application/json"
							}
						],
						"body": {
							"mode": "raw",
							"raw": "{\"id\":1,\"nomeartista\":\"Matueg\",\"pais\":\"Brasil\"}"
						},
						"url": {
							"raw": "http://localhost:8080/Artistas/1",
							"protocol": "http",
							"host": [
								"localhost"
							],
							"port": "8080",
							"path": [
								"Artistas",
								"1"
							]
						}
					},
					"response": []
				},
				{
					"name": "Delete Artist ID",
					"request": {
						"method": "DELETE",
						"header": [
							{
								"key": "accept",
								"value": "*/*"
							}
						],
						"url": {
							"raw": "http://localhost:8080/Artistas/3",
							"protocol": "http",
							"host": [
								"localhost"
							],
							"port": "8080",
							"path": [
								"Artistas",
								"3"
							]
						}
					},
					"response": []
				}
			]
		},
		{
			"name": "Musicas",
			"item": [
				{
					"name": "Show All Musics",
					"request": {
						"method": "GET",
						"header": [
							{
								"key": "accept",
								"value": "application/json"
							}
						],
						"url": {
							"raw": "http://localhost:8080/Musica",
							"protocol": "http",
							"host": [
								"localhost"
							],
							"port": "8080",
							"path": [
								"Musica"
							]
						}
					},
					"response": []
				},
				{
					"name": "Create Music",
					"request": {
						"method": "POST",
						"header": [
							{
								"key": "accept",
								"value": "application/json"
							},
							{
								"key": "Content-Type",
								"value": "application/json"
							}
						],
						"body": {
							"mode": "raw",
							"raw": "{\"id\":1,\"genero\":\"POP\",\"nomeartista\":\"testennomeartista\",\"nomeMusica\":\"Cant Get You Out Of My Head\",\"datadelancamento\":2000,\"album_id\":3}"
						},
						"url": {
							"raw": "http://localhost:8080/Musica",
							"protocol": "http",
							"host": [
								"localhost"
							],
							"port": "8080",
							"path": [
								"Musica"
							]
						}
					},
					"response": []
				},
				{
					"name": "Show Music ID",
					"request": {
						"method": "GET",
						"header": [
							{
								"key": "accept",
								"value": "application/json"
							}
						],
						"url": {
							"raw": "http://localhost:8080/Musica/1",
							"protocol": "http",
							"host": [
								"localhost"
							],
							"port": "8080",
							"path": [
								"Musica",
								"1"
							]
						}
					},
					"response": []
				},
				{
					"name": "Update Music ID",
					"request": {
						"method": "PUT",
						"header": [
							{
								"key": "accept",
								"value": "application/json"
							},
							{
								"key": "Content-Type",
								"value": "application/json"
							}
						],
						"body": {
							"mode": "raw",
							"raw": "{\"id\":1,\"genero\":\"POP\",\"nomeartista\":\"testenomeartista\",\"nomeMusica\":\"Cant Get You Out Of My Head\",\"datadelancamento\":2000,\"album_id\":2}"
						},
						"url": {
							"raw": "http://localhost:8080/Musica/1",
							"protocol": "http",
							"host": [
								"localhost"
							],
							"port": "8080",
							"path": [
								"Musica",
								"1"
							]
						}
					},
					"response": []
				},
				{
					"name": "Delete Music ID",
					"request": {
						"method": "DELETE",
						"header": [
							{
								"key": "accept",
								"value": "*/*"
							}
						],
						"url": {
							"raw": "http://localhost:8080/Musica/1",
							"protocol": "http",
							"host": [
								"localhost"
							],
							"port": "8080",
							"path": [
								"Musica",
								"1"
							]
						}
					},
					"response": []
				}
			]
		},
		{
			"name": "Albums",
			"item": [
				{
					"name": "Get Musics From AlbumID",
					"request": {
						"method": "GET",
						"header": [
							{
								"key": "accept",
								"value": "application/json"
							}
						],
						"url": {
							"raw": "http://localhost:8080/Albums/2/Musica",
							"protocol": "http",
							"host": [
								"localhost"
							],
							"port": "8080",
							"path": [
								"Albums",
								"2",
								"Musica"
							]
						}
					},
					"response": []
				},
				{
					"name": "Delete Music From AlbumID",
					"request": {
						"method": "DELETE",
						"header": [
							{
								"key": "accept",
								"value": "*/*"
							}
						],
						"url": {
							"raw": "http://localhost:8080/Albums/1/Musica",
							"protocol": "http",
							"host": [
								"localhost"
							],
							"port": "8080",
							"path": [
								"Albums",
								"1",
								"Musica"
							]
						}
					},
					"response": []
				}
			]
		}
	]
}